stispectrograph/__init__.py
stispectrograph/constants.py
stispectrograph/image.py
stispectrograph/io.py
stispectrograph/visualisation.py
stispectrograph-0.2.data/scripts/fits_to_csv.py
stispectrograph-0.2.dist-info/LICENSE.txt
stispectrograph-0.2.dist-info/METADATA
stispectrograph-0.2.dist-info/WHEEL
stispectrograph-0.2.dist-info/top_level.txt
stispectrograph-0.2.dist-info/RECORD
