Metadata-Version: 2.1
Name: stispectrograph
Version: 0.2
Summary: A replacement for "ST-i Spectroscopy Program" by SBIG.
Home-page: UNKNOWN
Author: Antoni Kowalik
Author-email: antonikowalik23@gmail.com
License: LICENSE.txt
Keywords: astronomy,spectrograph,sti,sbig
Platform: UNKNOWN
Classifier: Programming Language :: Python :: 3.8
Classifier: License :: OSI Approved :: MIT License
Classifier: Operating System :: OS Independent
Requires-Python: >=3.8
Requires-Dist: astropy
